flask_hashfs/__init__.py
flask_hashfs/__meta__.py
Flask_HashFS-0.3.0.dist-info/top_level.txt
Flask_HashFS-0.3.0.dist-info/METADATA
Flask_HashFS-0.3.0.dist-info/DESCRIPTION.rst
Flask_HashFS-0.3.0.dist-info/metadata.json
Flask_HashFS-0.3.0.dist-info/WHEEL
Flask_HashFS-0.3.0.dist-info/RECORD
