Metadata-Version: 2.0
Name: Flask-HashFS
Version: 0.3.0
Summary: Flask extension for HashFS, a content-addressable file management system.
Home-page: https://github.com/dgilland/flask-hashfs
Author: Derrick Gilland
Author-email: dgilland@gmail.com
License: MIT License
Keywords: flask hashfs hash file system content addressable fixed storage
Platform: UNKNOWN
Classifier: Development Status :: 2 - Pre-Alpha
Classifier: Intended Audience :: Developers
Classifier: Operating System :: OS Independent
Classifier: Programming Language :: Python
Classifier: License :: OSI Approved :: MIT License
Classifier: Topic :: Software Development :: Libraries
Classifier: Topic :: Software Development :: Libraries :: Python Modules
Classifier: Programming Language :: Python
Classifier: Programming Language :: Python :: 2
Classifier: Programming Language :: Python :: 2.7
Classifier: Programming Language :: Python :: 3
Classifier: Programming Language :: Python :: 3.3
Classifier: Programming Language :: Python :: 3.4
Requires-Dist: hashfs (>=0.3.0)
Requires-Dist: flask
